MANIFEST.in
README.md
setup.py
dash_responsive_grid_layout/__init__.py
dash_responsive_grid_layout/bundle.js
dash_responsive_grid_layout/metadata.json
dash_responsive_grid_layout/package.json
dash_responsive_grid_layout.egg-info/PKG-INFO
dash_responsive_grid_layout.egg-info/SOURCES.txt
dash_responsive_grid_layout.egg-info/dependency_links.txt
dash_responsive_grid_layout.egg-info/top_level.txt