Metadata-Version: 1.0
Name: dash-responsive-grid-layout
Version: 0.1.0
Summary: dash-responsive-grid-layout
Home-page: UNKNOWN
Author: Alex Cabello alexander.cabello@gmail.com
Author-email: UNKNOWN
License: MIT
Platform: UNKNOWN
